gf_api_client_test/__init__.py
gf_api_client_test/client.py
gf_api_client_test/conditions.py
gf_api_client_test-0.1.5.dist-info/licenses/LICENSE
gf_api_client_test-0.1.5.dist-info/METADATA
gf_api_client_test-0.1.5.dist-info/WHEEL
gf_api_client_test-0.1.5.dist-info/top_level.txt
gf_api_client_test-0.1.5.dist-info/RECORD
